marcktools/__init__.py
marcktools/server.py
marcktools-0.3.0.dist-info/METADATA
marcktools-0.3.0.dist-info/WHEEL
marcktools-0.3.0.dist-info/entry_points.txt
marcktools-0.3.0.dist-info/top_level.txt
marcktools-0.3.0.dist-info/RECORD
