Metadata-Version: 2.4
Name: marcktools
Version: 0.3.0
Summary: A simple demo with MCP stdio support
Author-email: marckwei <xiangwei1895@gmail.com>
Requires-Python: >=3.10
Requires-Dist: mcp>=1.6.0
